[
  {
    "name": "CECS 196- 2006建筑室内防水工程技术规程.pdf",
    "size": 0,
    "status": "completed",
    "uploadTime": "2025-10-04T06:08:57.371Z",
    "startTime": "2025-10-03T23:08:59.472040",
    "endTime": "2025-10-03T23:09:50.418149",
    "processingTime": null,
    "taskId": "53877c9c-11c3-4305-9810-d5956b2ad3d8",
    "progress": 100,
    "message": "转换完成",
    "errorMessage": null,
    "outputDir": "./output/53877c9c_11c3_4305_9810_d5956b2ad3d8_CECS_196__2006建筑室内防水工程技术规程_251003_230859/vlm"
  },
  {
    "name": "CJJ 14-2016：城市公共厕所设计标准.pdf",
    "size": 9900635,
    "status": "completed",
    "uploadTime": "2025-10-04T06:08:57.371Z",
    "startTime": "2025-10-03T23:09:50.815349",
    "endTime": "2025-10-03T23:11:01.238798",
    "processingTime": 70.423449,
    "taskId": "0de0dafc-4cc3-48bb-a314-98e976ec32bc",
    "progress": 100,
    "message": "转换完成",
    "errorMessage": null,
    "outputDir": "./output/0de0dafc_4cc3_48bb_a314_98e976ec32bc_CJJ_14_2016_城市公共厕所设计标准_251003_230951/vlm"
  },
  {
    "name": "CJJ 267-2017 动物园设计规范.pdf",
    "size": 1843278,
    "status": "completed",
    "uploadTime": "2025-10-04T06:08:57.372Z",
    "startTime": "2025-10-03T23:11:01.510057",
    "endTime": "2025-10-03T23:12:42.024501",
    "processingTime": 100.514444,
    "taskId": "4c62b180-dead-46c3-a42b-00ab4ea4cb9f",
    "progress": 100,
    "message": "转换完成",
    "errorMessage": null,
    "outputDir": "./output/4c62b180_dead_46c3_a42b_00ab4ea4cb9f_CJJ_267_2017_动物园设计规范_251003_231102/vlm"
  },
  {
    "name": "CJJ／T15-2011城市道路公共交通站、场、厂工程设计规范.pdf",
    "size": 3309639,
    "status": "completed",
    "uploadTime": "2025-10-04T06:08:57.373Z",
    "startTime": "2025-10-03T23:12:42.314574",
    "endTime": "2025-10-03T23:14:08.524914",
    "processingTime": 86.21034,
    "taskId": "40a91049-5f04-49c1-acdb-117c7de87868",
    "progress": 100,
    "message": "转换完成",
    "errorMessage": null,
    "outputDir": "./output/40a91049_5f04_49c1_acdb_117c7de87868_CJJ_T15_2011城市道路公共交通站_场_厂工程设计规范_251003_231242/vlm"
  },
  {
    "name": "CJJ／T300-2019植物园设计标准.pdf",
    "size": 2521526,
    "status": "completed",
    "uploadTime": "2025-10-04T06:08:57.373Z",
    "startTime": "2025-10-03T23:14:08.850647",
    "endTime": "2025-10-03T23:15:20.302012",
    "processingTime": 71.451365,
    "taskId": "56e8da41-2a54-432c-94cf-90483d88b192",
    "progress": 100,
    "message": "转换完成",
    "errorMessage": null,
    "outputDir": "./output/56e8da41_2a54_432c_94cf_90483d88b192_CJJ_T300_2019植物园设计标准_251003_231409/vlm"
  },
  {
    "name": "DBJ04 T 448-2023 植物园设计标准.pdf",
    "size": 20460553,
    "status": "completed",
    "uploadTime": "2025-10-04T06:08:57.373Z",
    "startTime": "2025-10-03T23:15:20.585618",
    "endTime": "2025-10-03T23:16:35.927641",
    "processingTime": 75.342023,
    "taskId": "0bb840ee-af92-465f-a8ed-ce8d6489fd0d",
    "progress": 100,
    "message": "转换完成",
    "errorMessage": null,
    "outputDir": "./output/0bb840ee_af92_465f_a8ed_ce8d6489fd0d_DBJ04_T_448_2023_植物园设计标准_251003_231521/vlm"
  },
  {
    "name": "DBJ04 T 450-2023 民用节水型建筑设计标准.pdf",
    "size": 21968216,
    "status": "completed",
    "uploadTime": "2025-10-04T06:08:57.373Z",
    "startTime": "2025-10-03T23:16:36.223961",
    "endTime": "2025-10-03T23:17:55.850010",
    "processingTime": 79.626049,
    "taskId": "1d453b90-b92e-4af4-8578-0287b2806c39",
    "progress": 100,
    "message": "转换完成",
    "errorMessage": null,
    "outputDir": "./output/1d453b90_b92e_4af4_8578_0287b2806c39_DBJ04_T_450_2023_民用节水型建筑设计标准_251003_231636/vlm"
  },
  {
    "name": "DBJ04 T 459-2023 近零能耗居住建筑技术标准.pdf",
    "size": 45093446,
    "status": "completed",
    "uploadTime": "2025-10-04T06:08:57.374Z",
    "startTime": "2025-10-03T23:17:56.115029",
    "endTime": "2025-10-03T23:21:00.460769",
    "processingTime": 184.34574,
    "taskId": "3cbaec31-ff07-4dfa-be89-628715eae2e4",
    "progress": 100,
    "message": "转换完成",
    "errorMessage": null,
    "outputDir": "./output/3cbaec31_ff07_4dfa_be89_628715eae2e4_DBJ04_T_459_2023_近零能耗居住建筑技术标准_251003_231756/vlm"
  },
  {
    "name": "DBJ04_T 241-2024 公共建筑节能设计标准.pdf",
    "size": 63032408,
    "status": "completed",
    "uploadTime": "2025-10-04T06:08:57.374Z",
    "startTime": "2025-10-03T23:21:00.757898",
    "endTime": "2025-10-03T23:24:39.941736",
    "processingTime": 219.183838,
    "taskId": "0bdfdf6c-2ba1-4012-8899-0907425a3f05",
    "progress": 100,
    "message": "转换完成",
    "errorMessage": null,
    "outputDir": "./output/0bdfdf6c_2ba1_4012_8899_0907425a3f05_DBJ04_T_241_2024_公共建筑节能设计标准_251003_232101/vlm"
  },
  {
    "name": "DBJ04_T 471-2024 既有建筑绿色化改造技术标准.pdf",
    "size": 66663098,
    "status": "completed",
    "uploadTime": "2025-10-04T06:08:57.374Z",
    "startTime": "2025-10-03T23:24:40.256712",
    "endTime": "2025-10-03T23:26:46.634930",
    "processingTime": 126.378218,
    "taskId": "23706961-675b-4170-8b25-9d384b804e13",
    "progress": 100,
    "message": "转换完成",
    "errorMessage": null,
    "outputDir": "./output/23706961_675b_4170_8b25_9d384b804e13_DBJ04_T_471_2024_既有建筑绿色化改造技术标准_251003_232440/vlm"
  },
  {
    "name": "DBJ04_T+461-2023+工业建筑节能设计标准.pdf",
    "size": 9470066,
    "status": "processing",
    "uploadTime": "2025-10-04T06:08:57.374Z",
    "startTime": "2025-10-03T23:26:46.911982",
    "endTime": null,
    "processingTime": null,
    "taskId": "02a59dcd-19f9-4f28-9ea4-6992dae6d36d",
    "progress": 20,
    "message": "开始处理文件",
    "errorMessage": null,
    "outputDir": null
  },
  {
    "name": "DBJ04+T246-2014建筑节能门窗应用技术规程.pdf",
    "size": 1645805,
    "status": "queued",
    "uploadTime": "2025-10-04T06:08:57.375Z",
    "startTime": null,
    "endTime": null,
    "processingTime": null,
    "taskId": "f9a85492-720c-43a1-99f2-afa4584ebd1d",
    "progress": 10,
    "message": "已加入队列",
    "errorMessage": null,
    "outputDir": null
  },
  {
    "name": "DBJ04-415-2021绿色建筑设计标准.pdf",
    "size": 77250927,
    "status": "queued",
    "uploadTime": "2025-10-04T06:08:57.375Z",
    "startTime": null,
    "endTime": null,
    "processingTime": null,
    "taskId": "795e7ba1-4850-411a-8c51-74fcb7325730",
    "progress": 10,
    "message": "已加入队列",
    "errorMessage": null,
    "outputDir": null
  },
  {
    "name": "DBJ04T 410-2021 城市停车场（库）设施配置标准.pdf",
    "size": 1803238,
    "status": "queued",
    "uploadTime": "2025-10-04T06:08:57.375Z",
    "startTime": null,
    "endTime": null,
    "processingTime": null,
    "taskId": "6b6d4c94-94ac-47d9-b9c5-8f0c01026a44",
    "progress": 10,
    "message": "已加入队列",
    "errorMessage": null,
    "outputDir": null
  },
  {
    "name": "DBJ04T 419-2021 建筑保温与外墙装饰防火设计指南.pdf",
    "size": 1733313,
    "status": "queued",
    "uploadTime": "2025-10-04T06:08:57.376Z",
    "startTime": null,
    "endTime": null,
    "processingTime": null,
    "taskId": "6fc30f0d-a2dd-44a9-941e-08b4fec734f2",
    "progress": 10,
    "message": "已加入队列",
    "errorMessage": null,
    "outputDir": null
  },
  {
    "name": "DBJ04T 436-2022装配式钢结构高层住宅建筑设计标准.pdf",
    "size": 20947437,
    "status": "queued",
    "uploadTime": "2025-10-04T06:08:57.376Z",
    "startTime": null,
    "endTime": null,
    "processingTime": null,
    "taskId": "6169e123-a10c-4f3e-b9b3-3ab53012bf6c",
    "progress": 10,
    "message": "已加入队列",
    "errorMessage": null,
    "outputDir": null
  },
  {
    "name": "DBJ04T 437-2023 宜居住宅建设标准.pdf",
    "size": 8708258,
    "status": "queued",
    "uploadTime": "2025-10-04T06:08:57.376Z",
    "startTime": null,
    "endTime": null,
    "processingTime": null,
    "taskId": "c3cb9526-15b8-4b5f-9971-ab866de4710b",
    "progress": 10,
    "message": "已加入队列",
    "errorMessage": null,
    "outputDir": null
  },
  {
    "name": "DBJ04T 440-2023电动自行车停放充电场所防火技术标准.pdf",
    "size": 777733,
    "status": "queued",
    "uploadTime": "2025-10-04T06:08:57.376Z",
    "startTime": null,
    "endTime": null,
    "processingTime": null,
    "taskId": "73b7bbc2-0465-4c61-b714-44ce5ee3459a",
    "progress": 10,
    "message": "已加入队列",
    "errorMessage": null,
    "outputDir": null
  },
  {
    "name": "DBJ04T 441-2023装配式钢结构建筑技术规程.pdf",
    "size": 6246974,
    "status": "queued",
    "uploadTime": "2025-10-04T06:08:57.377Z",
    "startTime": null,
    "endTime": null,
    "processingTime": null,
    "taskId": "ea14ba95-a514-4e82-a3fa-5f5f75f90dd1",
    "progress": 10,
    "message": "已加入队列",
    "errorMessage": null,
    "outputDir": null
  },
  {
    "name": "DBJ04T 442-2023装配式内装修技术标准.pdf",
    "size": 2843244,
    "status": "queued",
    "uploadTime": "2025-10-04T06:08:57.377Z",
    "startTime": null,
    "endTime": null,
    "processingTime": null,
    "taskId": "98f8604f-f7e8-4bc7-91f9-94ff4a87fd6e",
    "progress": 10,
    "message": "已加入队列",
    "errorMessage": null,
    "outputDir": null
  },
  {
    "name": "DBJ04T 460-2023既有公共建筑节能改造技术标准.pdf",
    "size": 5433801,
    "status": "queued",
    "uploadTime": "2025-10-04T06:08:57.377Z",
    "startTime": null,
    "endTime": null,
    "processingTime": null,
    "taskId": "e635c05c-00a8-43f8-ae65-42f69b5eb4a5",
    "progress": 10,
    "message": "已加入队列",
    "errorMessage": null,
    "outputDir": null
  },
  {
    "name": "DBJ04T+396-2019+装配式建筑评价标准.pdf",
    "size": 11802471,
    "status": "queued",
    "uploadTime": "2025-10-04T06:08:57.378Z",
    "startTime": null,
    "endTime": null,
    "processingTime": null,
    "taskId": "737443fa-ab2b-4cf1-a9f4-21364e41b246",
    "progress": 10,
    "message": "已加入队列",
    "errorMessage": null,
    "outputDir": null
  },
  {
    "name": "DBJ04-T398-2019电动汽车充电基础设施工程技术标准.pdf",
    "size": 4142552,
    "status": "queued",
    "uploadTime": "2025-10-04T06:08:57.378Z",
    "startTime": null,
    "endTime": null,
    "processingTime": null,
    "taskId": "516dcaa7-fde5-471f-a734-0fabc5b58532",
    "progress": 10,
    "message": "已加入队列",
    "errorMessage": null,
    "outputDir": null
  },
  {
    "name": "DBJ04T467-2023建筑防烟排烟系统技术标准.pdf",
    "size": 41041801,
    "status": "queued",
    "uploadTime": "2025-10-04T06:08:57.379Z",
    "startTime": null,
    "endTime": null,
    "processingTime": null,
    "taskId": "add7f85e-8492-44af-8685-85854e70314e",
    "progress": 10,
    "message": "已加入队列",
    "errorMessage": null,
    "outputDir": null
  },
  {
    "name": "JGJ 25-2010档案馆建筑设计规范.pdf",
    "size": 5473708,
    "status": "queued",
    "uploadTime": "2025-10-04T06:08:57.379Z",
    "startTime": null,
    "endTime": null,
    "processingTime": null,
    "taskId": "be2a2be6-357b-4f09-8a17-10377e2ab48f",
    "progress": 10,
    "message": "已加入队列",
    "errorMessage": null,
    "outputDir": null
  },
  {
    "name": "JGJ 26-2018严寒和寒冷地区居住建筑节能设计标准.pdf",
    "size": 8231301,
    "status": "queued",
    "uploadTime": "2025-10-04T06:08:57.380Z",
    "startTime": null,
    "endTime": null,
    "processingTime": null,
    "taskId": "b5416ab4-5d0e-4d1e-ad5c-8aa909a968e0",
    "progress": 10,
    "message": "已加入队列",
    "errorMessage": null,
    "outputDir": null
  },
  {
    "name": "JGJ 31-2003体育建筑设计规范.pdf",
    "size": 28541227,
    "status": "queued",
    "uploadTime": "2025-10-04T06:08:57.380Z",
    "startTime": null,
    "endTime": null,
    "processingTime": null,
    "taskId": "8daa8ca8-580c-4e5d-b188-589faa7adecb",
    "progress": 10,
    "message": "已加入队列",
    "errorMessage": null,
    "outputDir": null
  },
  {
    "name": "JGJ 38-2015图书馆建筑设计规范.pdf",
    "size": 3081195,
    "status": "queued",
    "uploadTime": "2025-10-04T06:08:57.380Z",
    "startTime": null,
    "endTime": null,
    "processingTime": null,
    "taskId": "74f9cbb5-b37e-446e-a722-3d8d58eaddc8",
    "progress": 10,
    "message": "已加入队列",
    "errorMessage": null,
    "outputDir": null
  },
  {
    "name": "JGJ 57-2016 剧场建筑设计规范.pdf",
    "size": 18301112,
    "status": "queued",
    "uploadTime": "2025-10-04T06:08:57.381Z",
    "startTime": null,
    "endTime": null,
    "processingTime": null,
    "taskId": "b7277dc1-9a79-43e4-9f4a-45b5c8b0892a",
    "progress": 10,
    "message": "已加入队列",
    "errorMessage": null,
    "outputDir": null
  },
  {
    "name": "JGJ 58-2008电影院建筑设计规范.pdf",
    "size": 1378537,
    "status": "queued",
    "uploadTime": "2025-10-04T06:08:57.381Z",
    "startTime": null,
    "endTime": null,
    "processingTime": null,
    "taskId": "4e7de4f5-0554-44c9-bb65-8f8015b075c2",
    "progress": 10,
    "message": "已加入队列",
    "errorMessage": null,
    "outputDir": null
  },
  {
    "name": "JGJ 62-2014旅馆建筑设计规范.pdf",
    "size": 625396,
    "status": "queued",
    "uploadTime": "2025-10-04T06:08:57.381Z",
    "startTime": null,
    "endTime": null,
    "processingTime": null,
    "taskId": "dbf0fb42-6bbd-488c-915a-8ed85b42303a",
    "progress": 10,
    "message": "已加入队列",
    "errorMessage": null,
    "outputDir": null
  },
  {
    "name": "JGJ 64-2017饮食建筑设计标准.pdf",
    "size": 2694269,
    "status": "queued",
    "uploadTime": "2025-10-04T06:08:57.382Z",
    "startTime": null,
    "endTime": null,
    "processingTime": null,
    "taskId": "34cdef7f-f1cd-44d2-93e7-5dfae735e675",
    "progress": 10,
    "message": "已加入队列",
    "errorMessage": null,
    "outputDir": null
  },
  {
    "name": "JGJ 66-2015博物馆建筑设计规范.pdf",
    "size": 6874162,
    "status": "queued",
    "uploadTime": "2025-10-04T06:08:57.383Z",
    "startTime": null,
    "endTime": null,
    "processingTime": null,
    "taskId": "4862163c-39c3-434a-afca-f56ad7db06e8",
    "progress": 10,
    "message": "已加入队列",
    "errorMessage": null,
    "outputDir": null
  },
  {
    "name": "JGJ 75-2012夏热冬暖地区居住建筑节能设计标准.pdf",
    "size": 6648615,
    "status": "queued",
    "uploadTime": "2025-10-04T06:08:57.383Z",
    "startTime": null,
    "endTime": null,
    "processingTime": null,
    "taskId": "600b60d2-496d-4b22-811c-d0b12294d800",
    "progress": 10,
    "message": "已加入队列",
    "errorMessage": null,
    "outputDir": null
  },
  {
    "name": "JGJ 76-2019特殊教育学校建筑设计标准.pdf",
    "size": 9516124,
    "status": "queued",
    "uploadTime": "2025-10-04T06:08:57.384Z",
    "startTime": null,
    "endTime": null,
    "processingTime": null,
    "taskId": "b673572d-fb16-4473-8366-4dd1fa2a92ec",
    "progress": 10,
    "message": "已加入队列",
    "errorMessage": null,
    "outputDir": null
  },
  {
    "name": "JGJ 91-2019科研建筑设计标准.pdf",
    "size": 5474114,
    "status": "queued",
    "uploadTime": "2025-10-04T06:08:57.384Z",
    "startTime": null,
    "endTime": null,
    "processingTime": null,
    "taskId": "2beb709d-2f42-4612-950b-b30683c90552",
    "progress": 10,
    "message": "已加入队列",
    "errorMessage": null,
    "outputDir": null
  },
  {
    "name": "JGJ 100-2015车库建筑设计规范.pdf",
    "size": 2192584,
    "status": "queued",
    "uploadTime": "2025-10-04T06:08:57.384Z",
    "startTime": null,
    "endTime": null,
    "processingTime": null,
    "taskId": "9e34cfee-aa6c-435d-92e4-470cc6e80f2c",
    "progress": 10,
    "message": "已加入队列",
    "errorMessage": null,
    "outputDir": null
  },
  {
    "name": "JGJ 113-2015 建筑玻璃应用技术规程.pdf",
    "size": 1630527,
    "status": "queued",
    "uploadTime": "2025-10-04T06:08:57.384Z",
    "startTime": null,
    "endTime": null,
    "processingTime": null,
    "taskId": "b4fad030-48bb-4add-8ff1-a249f35a35ac",
    "progress": 10,
    "message": "已加入队列",
    "errorMessage": null,
    "outputDir": null
  },
  {
    "name": "JGJ 124-1999 殡仪馆建筑设计规范.pdf",
    "size": 4016558,
    "status": "queued",
    "uploadTime": "2025-10-04T06:08:57.385Z",
    "startTime": null,
    "endTime": null,
    "processingTime": null,
    "taskId": "d955326d-7f5c-4bd6-8407-d0f829d2265d",
    "progress": 10,
    "message": "已加入队列",
    "errorMessage": null,
    "outputDir": null
  },
  {
    "name": "JGJ 134-2010夏热冬冷地区居住建筑节能设计标准.pdf",
    "size": 24850899,
    "status": "queued",
    "uploadTime": "2025-10-04T06:08:57.385Z",
    "startTime": null,
    "endTime": null,
    "processingTime": null,
    "taskId": "56e4de77-212c-4c4d-b51e-6fcd471385ba",
    "progress": 10,
    "message": "已加入队列",
    "errorMessage": null,
    "outputDir": null
  },
  {
    "name": "JGJ 156-2008镇（乡）村文化中心建筑设计规范.pdf",
    "size": 734925,
    "status": "queued",
    "uploadTime": "2025-10-04T06:08:57.386Z",
    "startTime": null,
    "endTime": null,
    "processingTime": null,
    "taskId": "93fa7f9e-f090-4bb9-9037-cdc95343eb70",
    "progress": 10,
    "message": "已加入队列",
    "errorMessage": null,
    "outputDir": null
  },
  {
    "name": "JGJ 446-2018监狱建筑设计标准.pdf",
    "size": 1962348,
    "status": "queued",
    "uploadTime": "2025-10-04T06:08:57.386Z",
    "startTime": null,
    "endTime": null,
    "processingTime": null,
    "taskId": "0ad5f240-eece-4821-a2a7-48ff1f3b889c",
    "progress": 10,
    "message": "已加入队列",
    "errorMessage": null,
    "outputDir": null
  },
  {
    "name": "JGJ 450-2018老年人照料设施建筑设计标准.pdf",
    "size": 1970245,
    "status": "queued",
    "uploadTime": "2025-10-04T06:08:57.386Z",
    "startTime": null,
    "endTime": null,
    "processingTime": null,
    "taskId": "2b95fc02-39b3-4c13-9706-4fa45522c978",
    "progress": 10,
    "message": "已加入队列",
    "errorMessage": null,
    "outputDir": null
  },
  {
    "name": "JGJ 475-2019 温和地区居住建筑节能设计标准（附条文说明）(建标网-www.jz321.net).pdf",
    "size": 2098431,
    "status": "queued",
    "uploadTime": "2025-10-04T06:08:57.387Z",
    "startTime": null,
    "endTime": null,
    "processingTime": null,
    "taskId": "61b73404-1789-4d11-83b8-74106a75df44",
    "progress": 10,
    "message": "已加入队列",
    "errorMessage": null,
    "outputDir": null
  },
  {
    "name": "JGJ／T60-2012交通客运站建筑设计规范.pdf",
    "size": 1904579,
    "status": "queued",
    "uploadTime": "2025-10-04T06:08:57.387Z",
    "startTime": null,
    "endTime": null,
    "processingTime": null,
    "taskId": "8b62c186-4ec5-4658-8c31-a9197390c2d7",
    "progress": 10,
    "message": "已加入队列",
    "errorMessage": null,
    "outputDir": null
  },
  {
    "name": "JGJ+T 398-2017装配式住宅建筑设计标准.pdf",
    "size": 2777888,
    "status": "queued",
    "uploadTime": "2025-10-04T06:08:57.387Z",
    "startTime": null,
    "endTime": null,
    "processingTime": null,
    "taskId": "710b765f-5788-4c4b-b8ee-cd96cf0e2c4a",
    "progress": 10,
    "message": "已加入队列",
    "errorMessage": null,
    "outputDir": null
  },
  {
    "name": "JGJ36-2016_宿舍建筑设计规范_设计规范.pdf",
    "size": 1175602,
    "status": "queued",
    "uploadTime": "2025-10-04T06:08:57.387Z",
    "startTime": null,
    "endTime": null,
    "processingTime": null,
    "taskId": "ad6b3881-654b-4a55-be6c-edce7a5931d9",
    "progress": 10,
    "message": "已加入队列",
    "errorMessage": null,
    "outputDir": null
  },
  {
    "name": "JGJ39-2016托儿所、幼儿园建筑设计规范.pdf",
    "size": 619028,
    "status": "queued",
    "uploadTime": "2025-10-04T06:08:57.388Z",
    "startTime": null,
    "endTime": null,
    "processingTime": null,
    "taskId": "99af525c-d6ed-429a-b402-723ffc2a5e51",
    "progress": 10,
    "message": "已加入队列",
    "errorMessage": null,
    "outputDir": null
  },
  {
    "name": "JGJ48-2014_商店建筑设计规范_设计规范.pdf",
    "size": 1535923,
    "status": "queued",
    "uploadTime": "2025-10-04T06:08:57.388Z",
    "startTime": null,
    "endTime": null,
    "processingTime": null,
    "taskId": "931783e7-07fd-4dee-b12a-a88818df4b13",
    "progress": 10,
    "message": "已加入队列",
    "errorMessage": null,
    "outputDir": null
  },
  {
    "name": "JGJ214-2010《铝合金门窗工程技术规范》.pdf",
    "size": 22586285,
    "status": "queued",
    "uploadTime": "2025-10-04T06:08:57.388Z",
    "startTime": null,
    "endTime": null,
    "processingTime": null,
    "taskId": "e3f2c607-0057-4399-8793-88b62da6761b",
    "progress": 10,
    "message": "已加入队列",
    "errorMessage": null,
    "outputDir": null
  },
  {
    "name": "JGJ218-2010《展览建筑设计规范》.pdf",
    "size": 18059921,
    "status": "queued",
    "uploadTime": "2025-10-04T06:08:57.388Z",
    "startTime": null,
    "endTime": null,
    "processingTime": null,
    "taskId": "9abfdc24-c061-4a46-8484-5fb8adaa24df",
    "progress": 10,
    "message": "已加入队列",
    "errorMessage": null,
    "outputDir": null
  },
  {
    "name": "JGJ289-2012建筑外墙外保温防火隔离带技术规程.pdf",
    "size": 6921545,
    "status": "queued",
    "uploadTime": "2025-10-04T06:08:57.389Z",
    "startTime": null,
    "endTime": null,
    "processingTime": null,
    "taskId": "d38211d2-bb16-4fa0-a6b1-2bc11d020ec6",
    "progress": 10,
    "message": "已加入队列",
    "errorMessage": null,
    "outputDir": null
  },
  {
    "name": "JGJT 17-2020 蒸压加气混凝土制品应用技术标准.pdf",
    "size": 19651721,
    "status": "queued",
    "uploadTime": "2025-10-04T06:08:57.389Z",
    "startTime": null,
    "endTime": null,
    "processingTime": null,
    "taskId": "7e081f47-120c-438b-b95d-85a149e5bf15",
    "progress": 10,
    "message": "已加入队列",
    "errorMessage": null,
    "outputDir": null
  },
  {
    "name": "JGJT 40-2019 疗养院建筑设计标准.pdf",
    "size": 1783240,
    "status": "queued",
    "uploadTime": "2025-10-04T06:08:57.389Z",
    "startTime": null,
    "endTime": null,
    "processingTime": null,
    "taskId": "ebcc9fc0-274c-456a-8699-6b9dc65744bf",
    "progress": 10,
    "message": "已加入队列",
    "errorMessage": null,
    "outputDir": null
  },
  {
    "name": "JGJT 326-2014 机械式停车库工程技术规范.pdf",
    "size": 14893895,
    "status": "queued",
    "uploadTime": "2025-10-04T06:08:57.390Z",
    "startTime": null,
    "endTime": null,
    "processingTime": null,
    "taskId": "52225b1d-ddd2-40d4-a20a-3ffc6a3dcb90",
    "progress": 10,
    "message": "已加入队列",
    "errorMessage": null,
    "outputDir": null
  },
  {
    "name": "JGJT 346-2014 建筑节能气象参数标准.pdf",
    "size": 3468477,
    "status": "queued",
    "uploadTime": "2025-10-04T06:08:57.390Z",
    "startTime": null,
    "endTime": null,
    "processingTime": null,
    "taskId": "203f5a31-fe93-48d2-a909-83b5b111fd3a",
    "progress": 10,
    "message": "已加入队列",
    "errorMessage": null,
    "outputDir": null
  },
  {
    "name": "JGJ-T41-2014文化馆建筑设计规范.pdf",
    "size": 1777921,
    "status": "queued",
    "uploadTime": "2025-10-04T06:08:57.390Z",
    "startTime": null,
    "endTime": null,
    "processingTime": null,
    "taskId": "6a58da31-df5d-4136-8c20-717c86710a73",
    "progress": 10,
    "message": "已加入队列",
    "errorMessage": null,
    "outputDir": null
  },
  {
    "name": "JGJ-T67-2019办公建筑设计标准.pdf",
    "size": 2639800,
    "status": "queued",
    "uploadTime": "2025-10-04T06:08:57.391Z",
    "startTime": null,
    "endTime": null,
    "processingTime": null,
    "taskId": "0aac5b2a-fd58-4799-9145-783819c7a29f",
    "progress": 10,
    "message": "已加入队列",
    "errorMessage": null,
    "outputDir": null
  },
  {
    "name": "JGJT397-2016 公墓和骨灰寄存建筑设计规范.pdf",
    "size": 5675307,
    "status": "queued",
    "uploadTime": "2025-10-04T06:08:57.391Z",
    "startTime": null,
    "endTime": null,
    "processingTime": null,
    "taskId": "4ca7ccd2-0806-4707-84ce-a8979e09d3e2",
    "progress": 10,
    "message": "已加入队列",
    "errorMessage": null,
    "outputDir": null
  },
  {
    "name": "JTT 1453-2023 综合客运枢纽设计规范.pdf",
    "size": 4379271,
    "status": "queued",
    "uploadTime": "2025-10-04T06:08:57.391Z",
    "startTime": null,
    "endTime": null,
    "processingTime": null,
    "taskId": "a9834838-119a-4c72-b9e1-4a31658cc248",
    "progress": 10,
    "message": "已加入队列",
    "errorMessage": null,
    "outputDir": null
  },
  {
    "name": "T／CECS 768-2020公寓建筑设计标准.pdf",
    "size": 1918841,
    "status": "queued",
    "uploadTime": "2025-10-04T06:08:57.391Z",
    "startTime": null,
    "endTime": null,
    "processingTime": null,
    "taskId": "e78ba912-57e6-4d32-8489-ee4e816cef31",
    "progress": 10,
    "message": "已加入队列",
    "errorMessage": null,
    "outputDir": null
  },
  {
    "name": "T-CECS24-2020钢结构防火涂料应用技术规程.pdf",
    "size": 537804,
    "status": "queued",
    "uploadTime": "2025-10-04T06:08:57.392Z",
    "startTime": null,
    "endTime": null,
    "processingTime": null,
    "taskId": "2f3b4279-97bf-4f44-b5f5-65459d7fa1c0",
    "progress": 10,
    "message": "已加入队列",
    "errorMessage": null,
    "outputDir": null
  },
  {
    "name": "建标 110-2021综合医院建设标准.pdf",
    "size": 1585658,
    "status": "queued",
    "uploadTime": "2025-10-04T06:08:57.392Z",
    "startTime": null,
    "endTime": null,
    "processingTime": null,
    "taskId": "2646b97c-ac09-47d3-8ff1-9ac9750f6930",
    "progress": 10,
    "message": "已加入队列",
    "errorMessage": null,
    "outputDir": null
  },
  {
    "name": "建标 173-2016传染病医院建设标准.pdf",
    "size": 419747,
    "status": "queued",
    "uploadTime": "2025-10-04T06:08:57.392Z",
    "startTime": null,
    "endTime": null,
    "processingTime": null,
    "taskId": "56c55fd7-2718-434d-a17e-3d76316fc2c2",
    "progress": 10,
    "message": "已加入队列",
    "errorMessage": null,
    "outputDir": null
  },
  {
    "name": "建标 175-2016幼儿园建设标准.pdf",
    "size": 1716457,
    "status": "queued",
    "uploadTime": "2025-10-04T06:08:57.392Z",
    "startTime": null,
    "endTime": null,
    "processingTime": null,
    "taskId": "906451cf-587c-4eea-8129-c441003076aa",
    "progress": 10,
    "message": "已加入队列",
    "errorMessage": null,
    "outputDir": null
  },
  {
    "name": "建标 193-2018公共美术馆建设标准.pdf",
    "size": 2117295,
    "status": "queued",
    "uploadTime": "2025-10-04T06:08:57.393Z",
    "startTime": null,
    "endTime": null,
    "processingTime": null,
    "taskId": "7bc78f96-b6c0-4bbc-bc6c-8144fa294d20",
    "progress": 10,
    "message": "已加入队列",
    "errorMessage": null,
    "outputDir": null
  }
]